Metadata-Version: 1.0
Name: g-and-b-probability
Version: 0.1
Summary: Gaussian and Binomial distribution package
Home-page: UNKNOWN
Author: Yinan Wu
Author-email: UNKNOWN
License: UNKNOWN
Platform: UNKNOWN
